spinview/__init__.py
spinview/DB/default.db
spinview/main.py
spinview/own_glyph/own_glyph.ply
spinview/spinview.py
spinview/spinview_callbacks/__init__.py
spinview/spinview_callbacks/activation_callbacks.py
spinview/spinview_callbacks/glyphs_callbacks.py
spinview/spinview_callbacks/rmesh_callbacks.py
spinview/spinview_callbacks/tmesh_callbacks.py
spinview/spinview_callbacks/utilities_callbacks.py
spinview/spinview_icon/SpinView_logo.svg
spinview/spinview_parsers/parsers.py
spinview/spinview_ui/__init__.py
spinview/spinview_ui/data.py
spinview/spinview_ui/denoise.py
spinview/spinview_ui/glyph.py
spinview/spinview_ui/object.py
spinview/spinview_ui/projection.py
spinview/spinview_ui/rmesh.py
spinview/spinview_ui/tmesh.py
spinview/spinview_ui/toolbar.py
spinview/spinview_ui/toolbar_drawer.py
spinview/spinview_utilities/profile_DB.py
spinview/spinview_utilities/utils.py
spinview/spinview_utilities/vis_pyvista.py
spinview-1.0.2.dist-info/entry_points.txt
spinview-1.0.2.dist-info/LICENSE
spinview-1.0.2.dist-info/METADATA
spinview-1.0.2.dist-info/WHEEL
spinview-1.0.2.dist-info/RECORD
