Metadata-Version: 2.1
Name: spinview
Version: 1.0.2
Summary: 
Author: qichenxu
Author-email: qichenx@kth.se
Requires-Python: >=3.9,<3.10
Classifier: Programming Language :: Python :: 3
Classifier: Programming Language :: Python :: 3.9
Requires-Dist: imageio[ffmpeg] (>=2.31.3,<3.0.0)
Requires-Dist: pandas (>=2.1.0,<3.0.0)
Requires-Dist: plotly (>=5.16.1,<6.0.0)
Requires-Dist: pyvista (==0.41.1)
Requires-Dist: pywebview (>=4.3.3,<5.0.0)
Requires-Dist: scipy (>=1.11.2,<2.0.0)
Requires-Dist: tqdm (>=4.66.1,<5.0.0)
Requires-Dist: trame (==2.5.2)
Requires-Dist: typer[all] (>=0.9.0,<0.10.0)
